quart_auth/__init__.py
quart_auth/basic_auth.py
quart_auth/extension.py
quart_auth/globals.py
quart_auth/py.typed
quart_auth-0.10.0.dist-info/LICENSE
quart_auth-0.10.0.dist-info/METADATA
quart_auth-0.10.0.dist-info/WHEEL
quart_auth-0.10.0.dist-info/RECORD
