Metadata-Version: 2.1
Name: quart-auth
Version: 0.10.0
Summary: A Quart extension to provide secure cookie authentication
Home-page: https://github.com/pgjones/quart-auth/
License: MIT
Author: pgjones
Author-email: philip.graham.jones@googlemail.com
Requires-Python: >=3.8
Classifier: Development Status :: 3 - Alpha
Classifier: Environment :: Web Environment
Classifier: Intended Audience :: Developers
Classifier: License :: OSI Approved :: MIT License
Classifier: Operating System :: OS Independent
Classifier: Programming Language :: Python
Classifier: Programming Language :: Python :: 3
Classifier: Programming Language :: Python :: 3.8
Classifier: Programming Language :: Python :: 3.9
Classifier: Programming Language :: Python :: 3.10
Classifier: Programming Language :: Python :: 3.11
Classifier: Programming Language :: Python :: 3.12
Classifier: Topic :: Internet :: WWW/HTTP :: Dynamic Content
Classifier: Topic :: Software Development :: Libraries :: Python Modules
Provides-Extra: docs
Requires-Dist: pydata_sphinx_theme ; extra == "docs"
Requires-Dist: quart (>=0.18)
Requires-Dist: typing_extensions ; python_version < "3.10"
Project-URL: Repository, https://github.com/pgjones/quart-auth/
